ai/backend/plugin/VERSION
ai/backend/plugin/__init__.py
ai/backend/plugin/cli.py
ai/backend/plugin/entrypoint.py
ai/backend/plugin/py.typed
backend_ai_plugin-26.1.0.dist-info/METADATA
backend_ai_plugin-26.1.0.dist-info/WHEEL
backend_ai_plugin-26.1.0.dist-info/entry_points.txt
backend_ai_plugin-26.1.0.dist-info/namespace_packages.txt
backend_ai_plugin-26.1.0.dist-info/top_level.txt
backend_ai_plugin-26.1.0.dist-info/RECORD
