Metadata-Version: 2.4
Name: backend.ai-plugin
Version: 26.1.0
Summary: Backend.AI Plugin Subsystem
Home-page: https://github.com/lablup/backend.ai
Author: Lablup Inc. and contributors
License: MIT
Project-URL: Documentation, https://docs.backend.ai/
Project-URL: Source, https://github.com/lablup/backend.ai
Classifier: Intended Audience :: Developers
Classifier: Operating System :: MacOS :: MacOS X
Classifier: Operating System :: POSIX :: Linux
Classifier: Programming Language :: Python
Classifier: Programming Language :: Python :: 3
Classifier: Environment :: No Input/Output (Daemon)
Classifier: Topic :: Scientific/Engineering
Classifier: Topic :: Software Development
Classifier: Development Status :: 5 - Production/Stable
Classifier: Programming Language :: Python :: 3.13
Classifier: License :: OSI Approved :: MIT License
Requires-Python: >=3.13,<3.14
Requires-Dist: backend.ai-common==26.1.0
Requires-Dist: backend.ai-logging==26.1.0
Requires-Dist: click~=8.1.7
Requires-Dist: colorama>=0.4.6
Requires-Dist: tabulate~=0.8.9
Requires-Dist: types-colorama
Requires-Dist: types-tabulate
Dynamic: author
Dynamic: classifier
Dynamic: description
Dynamic: description-content-type
Dynamic: home-page
Dynamic: license
Dynamic: project-url
Dynamic: requires-dist
Dynamic: requires-python
Dynamic: summary
